autosteper/__init__.py
autosteper/autosteper.py
autosteper/cage.py
autosteper/checker.py
autosteper/generator.py
autosteper/optimizers.py
autosteper/parallel_unit.py
autosteper/parser.py
autosteper/plotter.py
autosteper/tools.py
AutoSteper-2.1.1.dist-info/LICENSE.txt
AutoSteper-2.1.1.dist-info/METADATA
AutoSteper-2.1.1.dist-info/WHEEL
AutoSteper-2.1.1.dist-info/top_level.txt
AutoSteper-2.1.1.dist-info/RECORD
