Metadata-Version: 2.1
Name: AutoSteper
Version: 2.1.1
Summary: Automated Stepwise Addition Procedure for Extrafullerene.
Home-page: https://github.com/Franklalalala/AutoSteper
Author: Franklalalala
Author-email: franklalalala <1660810667@qq.com>
License: The MIT License (MIT)
Project-URL: Source, https://github.com/franklalalala/AutoSteper
Platform: any
Classifier: Programming Language :: Python
Classifier: Intended Audience :: Science/Research
Classifier: License :: OSI Approved :: MIT License
Classifier: Natural Language :: English
Classifier: Development Status :: 3 - Alpha
Requires-Python: >=3.8
License-File: LICENSE.txt
Requires-Dist: importlib-metadata
Requires-Dist: pytest-shutil
Requires-Dist: ase
Requires-Dist: numpy
Requires-Dist: pandas
Requires-Dist: networkx
Requires-Dist: tqdm
Requires-Dist: matplotlib (>=3.6.0)
Requires-Dist: seaborn
Requires-Dist: dpdispatcher
Requires-Dist: openpyxl
Provides-Extra: testing
Requires-Dist: setuptools ; extra == 'testing'
Requires-Dist: pytest ; extra == 'testing'
Requires-Dist: pytest-cov ; extra == 'testing'
